<SerializableDictionary>
	<item>
		<key>
			<string>ni-actorframework-aflib-src-1.0.1.0_70ae5257837d4513918a520c35307725.niaddoncache</string>
		</key>
		<value>
			<string>ni-actorframework-aflib-src-1.0.1.0.niaddoncache</string>
		</value>
	</item>
	<item>
		<key>
			<string>ni-analysis-advanced-src-1.0.8.5_feaa0d72a6d24e589a8ed2f14ee739cc.niaddoncache</string>
		</key>
		<value>
			<string>ni-analysis-advanced-src-1.0.8.5.niaddoncache</string>
		</value>
	</item>
	<item>
		<key>
			<string>ni-analysis-basic-src-1.0.8.6_c0aedbdfe1a34396bbe4d74163cf4734.niaddoncache</string>
		</key>
		<value>
			<string>ni-analysis-basic-src-1.0.8.6.niaddoncache</string>
		</value>
	</item>
	<item>
		<key>
			<string>ni-analysis-control-src-1.0.8.5_e83b89d8f1a64acfa049bf5da3b706e4.niaddoncache</string>
		</key>
		<value>
			<string>ni-analysis-control-src-1.0.8.5.niaddoncache</string>
		</value>
	</item>
	<item>
		<key>
			<string>ni-analysis-controlbasic-src-1.0.8.5_81610c9bdc044d78beec55ac0153bd2b.niaddoncache</string>
		</key>
		<value>
			<string>ni-analysis-controlbasic-src-1.0.8.5.niaddoncache</string>
		</value>
	</item>
	<item>
		<key>
			<string>ni-analysis-standard-src-1.0.8.4_65afcffe6d9f43f3a600371c93cffc8c.niaddoncache</string>
		</key>
		<value>
			<string>ni-analysis-standard-src-1.0.8.4.niaddoncache</string>
		</value>
	</item>
	<item>
		<key>
			<string>ni-fpga-fpgalib-src-4.0.0.6_b0ba8780031c4f32bba16590ba46504f.niaddoncache</string>
		</key>
		<value>
			<string>ni-fpga-fpgalib-src-4.0.0.6.niaddoncache</string>
		</value>
	</item>
	<item>
		<key>
			<string>ni-g-databaseconnectivity-src-1.0.0.0_319527715b248aea1415d361cec29e2.niaddoncache</string>
		</key>
		<value>
			<string>ni-g-databaseconnectivity-src-1.0.0.0.niaddoncache</string>
		</value>
	</item>
	<item>
		<key>
			<string>ni-g-http-src-1.0.0.16_21d77e1f29844de4969abeef0bb47576.niaddoncache</string>
		</key>
		<value>
			<string>ni-g-http-src-1.0.0.16.niaddoncache</string>
		</value>
	</item>
	<item>
		<key>
			<string>ni-g-reporting-src-1.0.0.13_74cbaf96b7894b77932bd4b128fac7d4.niaddoncache</string>
		</key>
		<value>
			<string>ni-g-reporting-src-1.0.0.13.niaddoncache</string>
		</value>
	</item>
	<item>
		<key>
			<string>ni-g-stdlib-src-1.0.6.45_d9b499cb7b22427f808e20f5e247c44b.niaddoncache</string>
		</key>
		<value>
			<string>ni-g-stdlib-src-1.0.6.45.niaddoncache</string>
		</value>
	</item>
	<item>
		<key>
			<string>ni-g-websockets-src-1.0.2.2_5e076ed048c94a4eb77b6be76bb64fb6.niaddoncache</string>
		</key>
		<value>
			<string>ni-g-websockets-src-1.0.2.2.niaddoncache</string>
		</value>
	</item>
	<item>
		<key>
			<string>ni-instrumentdriver-keysight344xx-src-20.0.0_4b57c96180d04ad0868d02357d3a6f32.niaddoncache</string>
		</key>
		<value>
			<string>ni-instrumentdriver-keysight344xx-src-20.0.0.niaddoncache</string>
		</value>
	</item>
	<item>
		<key>
			<string>ni-nativetarget-nativetargetlib-src-4.0.0.0_747036794f3e4750bb4768539d3c5d12.niaddoncache</string>
		</key>
		<value>
			<string>ni-nativetarget-nativetargetlib-src-4.0.0.0.niaddoncache</string>
		</value>
	</item>
	<item>
		<key>
			<string>ni-visa-base-src-20.0.0_3280a9d345304a34a72f3a8eaeb51641.niaddoncache</string>
		</key>
		<value>
			<string>ni-visa-base-src-20.0.0.niaddoncache</string>
		</value>
	</item>
	<item>
		<key>
			<string>WebApp_759.gcompcache</string>
		</key>
		<value>
			<string>WebApp.gcompcache</string>
		</value>
	</item>
	<item>
		<key>
			<string>ni-actorframework-aflib-src-1.0.1.0_c40ce8191d244e6abce8191a616b22ab.niaddoncache</string>
		</key>
		<value>
			<string>ni-actorframework-aflib-src-1.0.1.0_1.niaddoncache</string>
		</value>
	</item>
	<item>
		<key>
			<string>ni-analysis-advanced-src-1.0.8.5_24dda074a31143b9920ba5a5045ec646.niaddoncache</string>
		</key>
		<value>
			<string>ni-analysis-advanced-src-1.0.8.5_1.niaddoncache</string>
		</value>
	</item>
	<item>
		<key>
			<string>ni-analysis-basic-src-1.0.8.6_54b2b1453d6f4cbb85a5cbafb1a59d55.niaddoncache</string>
		</key>
		<value>
			<string>ni-analysis-basic-src-1.0.8.6_1.niaddoncache</string>
		</value>
	</item>
	<item>
		<key>
			<string>ni-analysis-control-src-1.0.8.5_e5c3e9e4269c4e9ea002c31872e078ef.niaddoncache</string>
		</key>
		<value>
			<string>ni-analysis-control-src-1.0.8.5_1.niaddoncache</string>
		</value>
	</item>
	<item>
		<key>
			<string>ni-analysis-controlbasic-src-1.0.8.5_e0ad08edc7ab495aa5d965f1435e6088.niaddoncache</string>
		</key>
		<value>
			<string>ni-analysis-controlbasic-src-1.0.8.5_1.niaddoncache</string>
		</value>
	</item>
	<item>
		<key>
			<string>ni-analysis-standard-src-1.0.8.4_1cb8d396a1824cdb90c0d554db936b13.niaddoncache</string>
		</key>
		<value>
			<string>ni-analysis-standard-src-1.0.8.4_1.niaddoncache</string>
		</value>
	</item>
	<item>
		<key>
			<string>ni-fpga-fpgalib-src-4.0.0.6_29f6bcd4386d4b0f8dc5a3b47311db24.niaddoncache</string>
		</key>
		<value>
			<string>ni-fpga-fpgalib-src-4.0.0.6_1.niaddoncache</string>
		</value>
	</item>
	<item>
		<key>
			<string>ni-g-databaseconnectivity-src-1.0.0.0_3501eb3a7b6b4e9c856f251079440ba7.niaddoncache</string>
		</key>
		<value>
			<string>ni-g-databaseconnectivity-src-1.0.0.0_1.niaddoncache</string>
		</value>
	</item>
	<item>
		<key>
			<string>ni-g-http-src-1.0.0.16_60271c27138541e4bb7210ce2072c47b.niaddoncache</string>
		</key>
		<value>
			<string>ni-g-http-src-1.0.0.16_1.niaddoncache</string>
		</value>
	</item>
	<item>
		<key>
			<string>ni-g-reporting-src-1.0.0.13_779fe30cdf49461e86fc3c8abd2914da.niaddoncache</string>
		</key>
		<value>
			<string>ni-g-reporting-src-1.0.0.13_1.niaddoncache</string>
		</value>
	</item>
	<item>
		<key>
			<string>ni-g-stdlib-src-1.0.6.45_371df03d4ec04ca2bd3a25115b9a223b.niaddoncache</string>
		</key>
		<value>
			<string>ni-g-stdlib-src-1.0.6.45_1.niaddoncache</string>
		</value>
	</item>
	<item>
		<key>
			<string>ni-g-websockets-src-1.0.2.2_1d1d8c25c8e34a468787a08e40194281.niaddoncache</string>
		</key>
		<value>
			<string>ni-g-websockets-src-1.0.2.2_1.niaddoncache</string>
		</value>
	</item>
	<item>
		<key>
			<string>ni-instrumentdriver-keysight344xx-src-20.0.0_a6da234ff3f54108a21c9c3fc54a1631.niaddoncache</string>
		</key>
		<value>
			<string>ni-instrumentdriver-keysight344xx-src-20.0.0_1.niaddoncache</string>
		</value>
	</item>
	<item>
		<key>
			<string>ni-nativetarget-nativetargetlib-src-4.0.0.0_cea10e32a7ad41b58b2828f352b7f152.niaddoncache</string>
		</key>
		<value>
			<string>ni-nativetarget-nativetargetlib-src-4.0.0.0_1.niaddoncache</string>
		</value>
	</item>
	<item>
		<key>
			<string>ni-visa-base-src-20.0.0_a6395e76640e42b9a239f8e2815adaae.niaddoncache</string>
		</key>
		<value>
			<string>ni-visa-base-src-20.0.0_1.niaddoncache</string>
		</value>
	</item>
	<item>
		<key>
			<string>GetHostname_e31b7bbad8ad436ab27d89a51f023896_759.jslicache</string>
		</key>
		<value>
			<string>GetHostname.jslicache</string>
		</value>
	</item>
	<item>
		<key>
			<string>NI.WebSockets_2fac1a9862694add9cf7441d9548d974_1d1d8c25c8e34a468787a08e40194281.gcompcache</string>
		</key>
		<value>
			<string>NI.WebSockets.gcompcache</string>
		</value>
	</item>
	<item>
		<key>
			<string>NI.G Core_5410850e559a427b9db7aaa900d640c7_371df03d4ec04ca2bd3a25115b9a223b.gcompcache</string>
		</key>
		<value>
			<string>NI.G Core.gcompcache</string>
		</value>
	</item>
	<item>
		<key>
			<string>Error_78745185e3294de397e9b4b977f08ad4_5410850e559a427b9db7aaa900d640c7_371df03d4ec04ca2bd3a25115b9a223b.gtypecache</string>
		</key>
		<value>
			<string>Error.gtypecache</string>
		</value>
	</item>
	<item>
		<key>
			<string>websocket_f4ac4cee74164fa39896fbe71021ca38_2fac1a9862694add9cf7441d9548d974_1d1d8c25c8e34a468787a08e40194281.jslicache</string>
		</key>
		<value>
			<string>websocket.jslicache</string>
		</value>
	</item>
	<item>
		<key>
			<string>error protocol_69e533219fcf4d3aaa9022ebe114363d_5410850e559a427b9db7aaa900d640c7_371df03d4ec04ca2bd3a25115b9a223b.gtypecache</string>
		</key>
		<value>
			<string>error protocol.gtypecache</string>
		</value>
	</item>
	<item>
		<key>
			<string>JSON (call chain)_f77d9d0b415c44a9914b0bbd84aa0d89_5410850e559a427b9db7aaa900d640c7_371df03d4ec04ca2bd3a25115b9a223b.gtypecache</string>
		</key>
		<value>
			<string>JSON (call chain).gtypecache</string>
		</value>
	</item>
	<item>
		<key>
			<string>ni-actorframework-aflib-src-1.0.1.0_ec92ab08353c4670a422a25373938e86.niaddoncache</string>
		</key>
		<value>
			<string>ni-actorframework-aflib-src-1.0.1.0_2.niaddoncache</string>
		</value>
	</item>
	<item>
		<key>
			<string>ni-analysis-advanced-src-1.0.8.5_9223176e5eed4598bead3ad4fd0c1acf.niaddoncache</string>
		</key>
		<value>
			<string>ni-analysis-advanced-src-1.0.8.5_2.niaddoncache</string>
		</value>
	</item>
	<item>
		<key>
			<string>ni-analysis-basic-src-1.0.8.6_358b45e7a2d94aa4ae7b822b785457ff.niaddoncache</string>
		</key>
		<value>
			<string>ni-analysis-basic-src-1.0.8.6_2.niaddoncache</string>
		</value>
	</item>
	<item>
		<key>
			<string>ni-analysis-control-src-1.0.8.5_5ce841e8591c45b593ba1040659583a3.niaddoncache</string>
		</key>
		<value>
			<string>ni-analysis-control-src-1.0.8.5_2.niaddoncache</string>
		</value>
	</item>
	<item>
		<key>
			<string>ni-analysis-controlbasic-src-1.0.8.5_b84bd34f191e4b70b97d294ab4c24c5c.niaddoncache</string>
		</key>
		<value>
			<string>ni-analysis-controlbasic-src-1.0.8.5_2.niaddoncache</string>
		</value>
	</item>
	<item>
		<key>
			<string>ni-analysis-standard-src-1.0.8.4_805615d8dd36486984f9bc5046b295bb.niaddoncache</string>
		</key>
		<value>
			<string>ni-analysis-standard-src-1.0.8.4_2.niaddoncache</string>
		</value>
	</item>
	<item>
		<key>
			<string>ni-fpga-fpgalib-src-4.0.0.6_bc6f3bdaa2e44542b7ec64e5b2fa2316.niaddoncache</string>
		</key>
		<value>
			<string>ni-fpga-fpgalib-src-4.0.0.6_2.niaddoncache</string>
		</value>
	</item>
	<item>
		<key>
			<string>ni-g-databaseconnectivity-src-1.0.0.0_73a19cc2cab043b7b44f96a92f57c891.niaddoncache</string>
		</key>
		<value>
			<string>ni-g-databaseconnectivity-src-1.0.0.0_2.niaddoncache</string>
		</value>
	</item>
	<item>
		<key>
			<string>ni-g-http-src-1.0.0.16_52ea4cd47431404daa59d76ac28d80f7.niaddoncache</string>
		</key>
		<value>
			<string>ni-g-http-src-1.0.0.16_2.niaddoncache</string>
		</value>
	</item>
	<item>
		<key>
			<string>ni-g-reporting-src-1.0.0.13_3353ce563e3249e3a34d0f518cf525f0.niaddoncache</string>
		</key>
		<value>
			<string>ni-g-reporting-src-1.0.0.13_2.niaddoncache</string>
		</value>
	</item>
	<item>
		<key>
			<string>ni-g-stdlib-src-1.0.6.45_bc0b22d9cd746c981be181640887def.niaddoncache</string>
		</key>
		<value>
			<string>ni-g-stdlib-src-1.0.6.45_2.niaddoncache</string>
		</value>
	</item>
	<item>
		<key>
			<string>ni-g-websockets-src-1.0.2.2_9cbcd06c924e46ba94128a61a4a8acf6.niaddoncache</string>
		</key>
		<value>
			<string>ni-g-websockets-src-1.0.2.2_2.niaddoncache</string>
		</value>
	</item>
	<item>
		<key>
			<string>ni-instrumentdriver-keysight344xx-src-20.0.0_6a3f27f673294bc7a8522b5bd1e60188.niaddoncache</string>
		</key>
		<value>
			<string>ni-instrumentdriver-keysight344xx-src-20.0.0_2.niaddoncache</string>
		</value>
	</item>
	<item>
		<key>
			<string>ni-nativetarget-nativetargetlib-src-4.0.0.0_2d79b9546c3e41eaa34a7db426ee01f9.niaddoncache</string>
		</key>
		<value>
			<string>ni-nativetarget-nativetargetlib-src-4.0.0.0_2.niaddoncache</string>
		</value>
	</item>
	<item>
		<key>
			<string>ni-visa-base-src-20.0.0_3cde131e05c841fb9c10a3462eb2acaf.niaddoncache</string>
		</key>
		<value>
			<string>ni-visa-base-src-20.0.0_2.niaddoncache</string>
		</value>
	</item>
	<item>
		<key>
			<string>ni-actorframework-aflib-src-1.0.1.0_9191b3a00e364ca2aa30be2730315326.niaddoncache</string>
		</key>
		<value>
			<string>ni-actorframework-aflib-src-1.0.1.0_3.niaddoncache</string>
		</value>
	</item>
	<item>
		<key>
			<string>ni-analysis-advanced-src-1.0.8.5_ffa2cc2cf60d480a9d2e62b35590ca07.niaddoncache</string>
		</key>
		<value>
			<string>ni-analysis-advanced-src-1.0.8.5_3.niaddoncache</string>
		</value>
	</item>
	<item>
		<key>
			<string>ni-analysis-basic-src-1.0.8.6_83892de79f4b44b78117683a2326fce3.niaddoncache</string>
		</key>
		<value>
			<string>ni-analysis-basic-src-1.0.8.6_3.niaddoncache</string>
		</value>
	</item>
	<item>
		<key>
			<string>ni-analysis-control-src-1.0.8.5_f0cb4325cbb14aceacf63d00303167af.niaddoncache</string>
		</key>
		<value>
			<string>ni-analysis-control-src-1.0.8.5_3.niaddoncache</string>
		</value>
	</item>
	<item>
		<key>
			<string>ni-analysis-controlbasic-src-1.0.8.5_76ba53db2c524d6ebc4568a9c6e778f8.niaddoncache</string>
		</key>
		<value>
			<string>ni-analysis-controlbasic-src-1.0.8.5_3.niaddoncache</string>
		</value>
	</item>
	<item>
		<key>
			<string>ni-analysis-standard-src-1.0.8.4_43c90abc43344d2593b749447a85e96e.niaddoncache</string>
		</key>
		<value>
			<string>ni-analysis-standard-src-1.0.8.4_3.niaddoncache</string>
		</value>
	</item>
	<item>
		<key>
			<string>ni-fpga-fpgalib-src-4.0.0.6_47a5fd525c5a48758585bb9433eccd6c.niaddoncache</string>
		</key>
		<value>
			<string>ni-fpga-fpgalib-src-4.0.0.6_3.niaddoncache</string>
		</value>
	</item>
	<item>
		<key>
			<string>ni-g-databaseconnectivity-src-1.0.0.0_e9cc3384c33543c4877fc211eeda4c55.niaddoncache</string>
		</key>
		<value>
			<string>ni-g-databaseconnectivity-src-1.0.0.0_3.niaddoncache</string>
		</value>
	</item>
	<item>
		<key>
			<string>ni-g-http-src-1.0.0.16_99f88f65e32345018e2e96fcb596110d.niaddoncache</string>
		</key>
		<value>
			<string>ni-g-http-src-1.0.0.16_3.niaddoncache</string>
		</value>
	</item>
	<item>
		<key>
			<string>ni-g-reporting-src-1.0.0.13_f1935cbdabf04a09b89035fb6d07d4ac.niaddoncache</string>
		</key>
		<value>
			<string>ni-g-reporting-src-1.0.0.13_3.niaddoncache</string>
		</value>
	</item>
	<item>
		<key>
			<string>ni-g-stdlib-src-1.0.6.45_5ab0d4aca3b54ef7b96dcb3d00cbef10.niaddoncache</string>
		</key>
		<value>
			<string>ni-g-stdlib-src-1.0.6.45_3.niaddoncache</string>
		</value>
	</item>
	<item>
		<key>
			<string>ni-g-websockets-src-1.0.2.2_9afd0b9d10a84dac88b8c5dc8a9177dd.niaddoncache</string>
		</key>
		<value>
			<string>ni-g-websockets-src-1.0.2.2_3.niaddoncache</string>
		</value>
	</item>
	<item>
		<key>
			<string>ni-instrumentdriver-keysight344xx-src-20.0.0_7592149b3d994e8c92a3069a40166e8c.niaddoncache</string>
		</key>
		<value>
			<string>ni-instrumentdriver-keysight344xx-src-20.0.0_3.niaddoncache</string>
		</value>
	</item>
	<item>
		<key>
			<string>ni-nativetarget-nativetargetlib-src-4.0.0.0_82c6d4e31c7f424ba34dbe10449fce28.niaddoncache</string>
		</key>
		<value>
			<string>ni-nativetarget-nativetargetlib-src-4.0.0.0_3.niaddoncache</string>
		</value>
	</item>
	<item>
		<key>
			<string>ni-visa-base-src-20.0.0_d98261ff3d4f450e830eb6b71331acd7.niaddoncache</string>
		</key>
		<value>
			<string>ni-visa-base-src-20.0.0_3.niaddoncache</string>
		</value>
	</item>
	<item>
		<key>
			<string>NI.WebSockets_2fac1a9862694add9cf7441d9548d974_9afd0b9d10a84dac88b8c5dc8a9177dd.gcompcache</string>
		</key>
		<value>
			<string>NI.WebSockets_1.gcompcache</string>
		</value>
	</item>
	<item>
		<key>
			<string>NI.G Core_5410850e559a427b9db7aaa900d640c7_5ab0d4aca3b54ef7b96dcb3d00cbef10.gcompcache</string>
		</key>
		<value>
			<string>NI.G Core_1.gcompcache</string>
		</value>
	</item>
	<item>
		<key>
			<string>websocket_f4ac4cee74164fa39896fbe71021ca38_2fac1a9862694add9cf7441d9548d974_9afd0b9d10a84dac88b8c5dc8a9177dd.jslicache</string>
		</key>
		<value>
			<string>websocket_1.jslicache</string>
		</value>
	</item>
	<item>
		<key>
			<string>Error_78745185e3294de397e9b4b977f08ad4_5410850e559a427b9db7aaa900d640c7_5ab0d4aca3b54ef7b96dcb3d00cbef10.gtypecache</string>
		</key>
		<value>
			<string>Error_1.gtypecache</string>
		</value>
	</item>
	<item>
		<key>
			<string>data_6c13b657158f414a9235ae7b1906f8de.xmlcache</string>
		</key>
		<value>
			<string>data.xmlcache</string>
		</value>
	</item>
	<item>
		<key>
			<string>Type_92c20ce844a042e98307a8d81d1b88b2_759.gtypecache</string>
		</key>
		<value>
			<string>Type.gtypecache</string>
		</value>
	</item>
	<item>
		<key>
			<string>Satates_92c20ce844a042e98307a8d81d1b88b2_759.gtypecache</string>
		</key>
		<value>
			<string>Satates.gtypecache</string>
		</value>
	</item>
	<item>
		<key>
			<string>NI.G Core.Color Picker_1419b18ca5a442569a83800b0bf40cfd_5ab0d4aca3b54ef7b96dcb3d00cbef10.gcompcache</string>
		</key>
		<value>
			<string>NI.G Core.Color Picker.gcompcache</string>
		</value>
	</item>
	<item>
		<key>
			<string>Color_20_1419b18ca5a442569a83800b0bf40cfd_5ab0d4aca3b54ef7b96dcb3d00cbef10.gtypecache</string>
		</key>
		<value>
			<string>Color.gtypecache</string>
		</value>
	</item>
</SerializableDictionary>